Quartus/lpm_mux.sv
module lpm_mux #(
		parameter WIDTH = 5
	)(
		input logic sel,
		input logic [WIDTH-1:0] data0,
		input logic [WIDTH-1:0] data1,
		output logic [WIDTH-1:0] result
	);

    always_comb begin
        case (sel)
            1'b0: result = data0;
            1'b1: result = data1;
        endcase
    end

endmodule

Quartus/d_flipflop.sv
module d_flipflop (
		input logic clk,
		input logic reset,
		input logic d,
		output logic q
	);

    always_ff @(posedge clk or posedge reset) begin
        if (reset)
            q <= 1'b0;
        else
            q <= d;
    end

endmodule

Quartus/lpm_counter.sv
module lpm_counter #(
		parameter WIDTH = 5
	)(
		input logic clk,
		input logic reset,
		output logic [WIDTH-1:0] q
	);

    always_ff @(posedge clk or posedge reset) begin
        if (reset)
            q <= 0;
        else
            q <= q + 1;
    end

endmodule

Quartus/lab6.sv
module lab6 (
		input  logic clk,
		input  logic reset,
		output logic [4:0] result
	);
    logic [4:0] counter_out;
    logic [2:0] pause_counter;
    logic       in_pause, next_in_pause;

    //Основной счетчик до 20
    lpm_counter #(.WIDTH(5)) counter_inst (
        .clk(clk),
        .reset(reset | in_pause),  //сбрасываем, если пауза началась
        .q(counter_out)
    );

    //Регистр паузы (от 0 до 5)
    always_ff @(posedge clk or posedge reset) begin
        if (reset) begin
            pause_counter <= 3'd0;
        end else if (in_pause) begin
            pause_counter <= pause_counter + 3'd1;
        end else begin
            pause_counter <= 3'd0;
        end
    end

    //Логика перехода in_pause
    always_comb begin
        if (reset)
            next_in_pause = 1'b0;
        else if (!in_pause && counter_out == 5'd20)
            next_in_pause = 1'b1;
        else if (in_pause && pause_counter == 3'd5)
            next_in_pause = 1'b0;
        else
            next_in_pause = in_pause;
    end

    //Хранение in_pause через D-триггер
    d_flipflop pause_ff (
        .clk(clk),
        .reset(reset),
        .d(next_in_pause),
        .q(in_pause)
    );

    //Мультиплексор
    lpm_mux #(.WIDTH(5)) result_mux (
        .sel(in_pause),
        .data0(counter_out),
        .data1(5'd0),
        .result(result)
    );
endmodule

Quartus/lab6_tb.sv
`timescale 1ns/100ps

module lab6_tb;
    logic clk;
    logic reset;
    logic [4:0] result;

    //Подключаем основной модуль
    lab6 uut (
        .clk(clk),
        .reset(reset),
        .result(result)
    );

    always #50 clk = ~clk;  //Один такт длится 100 нс

    initial begin
        // Инициализация
        $dumpfile("lab6.vcd");       // VCD-файл для просмотра в GTKWave
        $dumpvars(0, lab6_tb);       // Сохраняем все сигналы

        clk = 0;
        reset = 1;
        #20;                         // 20 нс держим сброс
        reset = 0;

        #6000;                       // работа 6000 нс
        $finish;
    end
endmodule

Quartus/lab6.vcd
$date
	Wed Apr 09 21:06:23 2025
$end
$version
	Icarus Verilog
$end
$timescale
	1ps
$end
$scope module lab6_tb $end
$var wire 5 ! result [4:0] $end
$var reg 1 " clk $end
$var reg 1 # reset $end
$scope module uut $end
$var wire 1 " clk $end
$var wire 1 # reset $end
$var wire 5 $ result [4:0] $end
$var wire 1 % in_pause $end
$var wire 5 & counter_out [4:0] $end
$var reg 1 ' next_in_pause $end
$var reg 3 ( pause_counter [2:0] $end
$scope module counter_inst $end
$var wire 1 " clk $end
$var wire 1 ) reset $end
$var parameter 32 * WIDTH $end
$var reg 5 + q [4:0] $end
$upscope $end
$scope module pause_ff $end
$var wire 1 " clk $end
$var wire 1 ' d $end
$var wire 1 # reset $end
$var reg 1 % q $end
$upscope $end
$scope module result_mux $end
$var wire 5 , data0 [4:0] $end
$var wire 5 - data1 [4:0] $end
$var wire 1 % sel $end
$var parameter 32 . WIDTH $end
$var reg 5 / result [4:0] $end
$upscope $end
$upscope $end
$upscope $end
$enddefinitions $end
$comment Show the parameter values. $end
$dumpall
b101 .
b101 *
$end
#0
$dumpvars
b0 /
b0 -
b0 ,
b0 +
1)
b0 (
0'
b0 &
0%
b0 $
1#
0"
b0 !
$end
#20000
0)
0#
#50000
b1 !
b1 $
b1 /
b1 &
b1 +
b1 ,
1"
#100000
0"
#150000
b10 !
b10 $
b10 /
b10 &
b10 +
b10 ,
1"
#200000
0"
#250000
b11 !
b11 $
b11 /
b11 &
b11 +
b11 ,
1"
#300000
0"
#350000
b100 !
b100 $
b100 /
b100 &
b100 +
b100 ,
1"
#400000
0"
#450000
b101 !
b101 $
b101 /
b101 &
b101 +
b101 ,
1"
#500000
0"
#550000
b110 !
b110 $
b110 /
b110 &
b110 +
b110 ,
1"
#600000
0"
#650000
b111 !
b111 $
b111 /
b111 &
b111 +
b111 ,
1"
#700000
0"
#750000
b1000 !
b1000 $
b1000 /
b1000 &
b1000 +
b1000 ,
1"
#800000
0"
#850000
b1001 !
b1001 $
b1001 /
b1001 &
b1001 +
b1001 ,
1"
#900000
0"
#950000
b1010 !
b1010 $
b1010 /
b1010 &
b1010 +
b1010 ,
1"
#1000000
0"
#1050000
b1011 !
b1011 $
b1011 /
b1011 &
b1011 +
b1011 ,
1"
#1100000
0"
#1150000
b1100 !
b1100 $
b1100 /
b1100 &
b1100 +
b1100 ,
1"
#1200000
0"
#1250000
b1101 !
b1101 $
b1101 /
b1101 &
b1101 +
b1101 ,
1"
#1300000
0"
#1350000
b1110 !
b1110 $
b1110 /
b1110 &
b1110 +
b1110 ,
1"
#1400000
0"
#1450000
b1111 !
b1111 $
b1111 /
b1111 &
b1111 +
b1111 ,
1"
#1500000
0"
#1550000
b10000 !
b10000 $
b10000 /
b10000 &
b10000 +
b10000 ,
1"
#1600000
0"
#1650000
b10001 !
b10001 $
b10001 /
b10001 &
b10001 +
b10001 ,
1"
#1700000
0"
#1750000
b10010 !
b10010 $
b10010 /
b10010 &
b10010 +
b10010 ,
1"
#1800000
0"
#1850000
b10011 !
b10011 $
b10011 /
b10011 &
b10011 +
b10011 ,
1"
#1900000
0"
#1950000
b10100 !
b10100 $
b10100 /
1'
b10100 &
b10100 +
b10100 ,
1"
#2000000
0"
#2050000
b0 !
b0 $
b0 /
1)
b0 &
b0 +
b0 ,
1%
1"
#2100000
0"
#2150000
b1 (
1"
#2200000
0"
#2250000
b10 (
1"
#2300000
0"
#2350000
b11 (
1"
#2400000
0"
#2450000
b100 (
1"
#2500000
0"
#2550000
0'
b101 (
1"
#2600000
0"
#2650000
0)
b110 (
0%
1"
#2700000
0"
#2750000
b1 !
b1 $
b1 /
b1 &
b1 +
b1 ,
b0 (
1"
#2800000
0"
#2850000
b10 !
b10 $
b10 /
b10 &
b10 +
b10 ,
1"
#2900000
0"
#2950000
b11 !
b11 $
b11 /
b11 &
b11 +
b11 ,
1"
#3000000
0"
#3050000
b100 !
b100 $
b100 /
b100 &
b100 +
b100 ,
1"
#3100000
0"
#3150000
b101 !
b101 $
b101 /
b101 &
b101 +
b101 ,
1"
#3200000
0"
#3250000
b110 !
b110 $
b110 /
b110 &
b110 +
b110 ,
1"
#3300000
0"
#3350000
b111 !
b111 $
b111 /
b111 &
b111 +
b111 ,
1"
#3400000
0"
#3450000
b1000 !
b1000 $
b1000 /
b1000 &
b1000 +
b1000 ,
1"
#3500000
0"
#3550000
b1001 !
b1001 $
b1001 /
b1001 &
b1001 +
b1001 ,
1"
#3600000
0"
#3650000
b1010 !
b1010 $
b1010 /
b1010 &
b1010 +
b1010 ,
1"
#3700000
0"
#3750000
b1011 !
b1011 $
b1011 /
b1011 &
b1011 +
b1011 ,
1"
#3800000
0"
#3850000
b1100 !
b1100 $
b1100 /
b1100 &
b1100 +
b1100 ,
1"
#3900000
0"
#3950000
b1101 !
b1101 $
b1101 /
b1101 &
b1101 +
b1101 ,
1"
#4000000
0"
#4050000
b1110 !
b1110 $
b1110 /
b1110 &
b1110 +
b1110 ,
1"
#4100000
0"
#4150000
b1111 !
b1111 $
b1111 /
b1111 &
b1111 +
b1111 ,
1"
#4200000
0"
#4250000
b10000 !
b10000 $
b10000 /
b10000 &
b10000 +
b10000 ,
1"
#4300000
0"
#4350000
b10001 !
b10001 $
b10001 /
b10001 &
b10001 +
b10001 ,
1"
#4400000
0"
#4450000
b10010 !
b10010 $
b10010 /
b10010 &
b10010 +
b10010 ,
1"
#4500000
0"
#4550000
b10011 !
b10011 $
b10011 /
b10011 &
b10011 +
b10011 ,
1"
#4600000
0"
#4650000
b10100 !
b10100 $
b10100 /
1'
b10100 &
b10100 +
b10100 ,
1"
#4700000
0"
#4750000
b0 !
b0 $
b0 /
1)
b0 &
b0 +
b0 ,
1%
1"
#4800000
0"
#4850000
b1 (
1"
#4900000
0"
#4950000
b10 (
1"
#5000000
0"
#5050000
b11 (
1"
#5100000
0"
#5150000
b100 (
1"
#5200000
0"
#5250000
0'
b101 (
1"
#5300000
0"
#5350000
0)
0%
b110 (
1"
#5400000
0"
#5450000
b1 !
b1 $
b1 /
b1 &
b1 +
b1 ,
b0 (
1"
#5500000
0"
#5550000
b10 !
b10 $
b10 /
b10 &
b10 +
b10 ,
1"
#5600000
0"
#5650000
b11 !
b11 $
b11 /
b11 &
b11 +
b11 ,
1"
#5700000
0"
#5750000
b100 !
b100 $
b100 /
b100 &
b100 +
b100 ,
1"
#5800000
0"
#5850000
b101 !
b101 $
b101 /
b101 &
b101 +
b101 ,
1"
#5900000
0"
#5950000
b110 !
b110 $
b110 /
b110 &
b110 +
b110 ,
1"
#6000000
0"
#6050000
b111 !
b111 $
b111 /
b111 &
b111 +
b111 ,
1"
#6100000
0"
#6150000
b1000 !
b1000 $
b1000 /
b1000 &
b1000 +
b1000 ,
1"
#6200000
0"
#6250000
b1001 !
b1001 $
b1001 /
b1001 &
b1001 +
b1001 ,
1"
#6300000
0"
#6350000
b1010 !
b1010 $
b1010 /
b1010 &
b1010 +
b1010 ,
1"
#6400000
0"
#6450000
b1011 !
b1011 $
b1011 /
b1011 &
b1011 +
b1011 ,
1"
#6500000
0"
#6550000
b1100 !
b1100 $
b1100 /
b1100 &
b1100 +
b1100 ,
1"
#6600000
0"
#6650000
b1101 !
b1101 $
b1101 /
b1101 &
b1101 +
b1101 ,
1"
#6700000
0"
#6750000
b1110 !
b1110 $
b1110 /
b1110 &
b1110 +
b1110 ,
1"
#6800000
0"
#6850000
b1111 !
b1111 $
b1111 /
b1111 &
b1111 +
b1111 ,
1"
#6900000
0"
#6950000
b10000 !
b10000 $
b10000 /
b10000 &
b10000 +
b10000 ,
1"
#7000000
0"
#7050000
b10001 !
b10001 $
b10001 /
b10001 &
b10001 +
b10001 ,
1"
#7100000
0"
#7150000
b10010 !
b10010 $
b10010 /
b10010 &
b10010 +
b10010 ,
1"
#7200000
0"
#7250000
b10011 !
b10011 $
b10011 /
b10011 &
b10011 +
b10011 ,
1"
#7300000
0"
#7350000
b10100 !
b10100 $
b10100 /
1'
b10100 &
b10100 +
b10100 ,
1"
#7400000
0"
#7450000
b0 !
b0 $
b0 /
1)
b0 &
b0 +
b0 ,
1%
1"
#7500000
0"
#7550000
b1 (
1"
#7600000
0"
#7650000
b10 (
1"
#7700000
0"
#7750000
b11 (
1"
#7800000
0"
#7850000
b100 (
1"
#7900000
0"
#7950000
0'
b101 (
1"
